MANIFEST.in
README.rst
setup.py
django_secdownload_storage.egg-info/PKG-INFO
django_secdownload_storage.egg-info/SOURCES.txt
django_secdownload_storage.egg-info/dependency_links.txt
django_secdownload_storage.egg-info/top_level.txt
secdownload_storage/__init__.py