Metadata-Version: 1.0
Name: django-secdownload-storage
Version: 0.1.1
Summary: Django storage backend that can be used to serve files via lighttpd's mod_secdownload module. This 
Home-page: https://bitbucket.org/ionelmc/django-secdownload-storage
Author: Ionel Mărieș Cristian
Author-email: ionel.mc@gmail.com
License: BSD
Platform: UNKNOWN
Classifier: Development Status :: 4 - Beta
Classifier: Framework :: Django
Classifier: Intended Audience :: Developers
Classifier: License :: OSI Approved :: BSD License
Classifier: Operating System :: OS Independent
Classifier: Programming Language :: Python
Classifier: Topic :: Internet :: WWW/HTTP
